{
  "title": "Challenge3",
  "stage": [
    {
      "title": "Challenge3-1",
      "name": "Challenge3-1",
	  "grid": [
        0,
        0
      ],
      "wave": [
        {
          "title": "wave1",
          "enemylist": [
            {
              "index": "FABigChick_Challenge3",
              "level": 90
            },
            {
              "index": "",
              "level": 0
            },
            {
              "index": "",
              "level": 0
            },
            {
              "index": "FABigChick_Challenge3",
              "level": 90
            },
            {
              "index": "FABigChick_Challenge1",
              "level": 90
            },
            {
              "index": "Predator_Challenge3",
              "level": 90
            },
            {
              "index": "FABigChick_Challenge3",
              "level": 90
            },
            {
              "index": "",
              "level": 0
            },
            {
              "index": "",
              "level": 0
            }
          ]
        }
      ]
    },
	{
      "title": "Challenge3-2",
      "name": "Challenge3-2",
	  "grid": [
        1,
        0
      ],
      "wave": [
        {
          "title": "wave1",
          "enemylist": [
            {
              "index": "FABigChick_Challenge3",
              "level": 85
            },
            {
              "index": "FABigChick_Challenge1",
              "level": 85
            },
            {
              "index": "",
              "level": 0
            },
            {
              "index": "FABigChick_Challenge3",
              "level": 85
            },
            {
              "index": "FABigChick_Challenge3",
              "level": 85
            },
            {
              "index": "Predator_Challenge3",
              "level": 85
            },
            {
              "index": "FABigChick_Challenge3",
              "level": 85
            },
            {
              "index": "FABigChick_Challenge1",
              "level": 85
            },
            {
              "index": "",
              "level": 0
            }
          ]
        }
      ]
    },
	{
      "title": "Challenge3-3",
      "name": "Challenge3-3",
	  "grid": [
        2,
        0
      ],
      "wave": [
        {
          "title": "wave1",
          "enemylist": [
            {
              "index": "FABigChick_Challenge1",
              "level": 80
            },
            {
              "index": "FABigChick_Challenge1",
              "level": 80
            },
            {
              "index": "",
              "level": 0
            },
            {
              "index": "FABigChick_Challenge1",
              "level": 80
            },
            {
              "index": "",
              "level": 0
            },
            {
              "index": "Predator_Challenge3",
              "level": 80
            },
            {
              "index": "FABigChick_Challenge1",
              "level": 80
            },
            {
              "index": "FABigChick_Challenge1",
              "level": 80
            },
            {
              "index": "",
              "level": 0
            }
          ]
        }
      ]
    },
	{
      "title": "Challenge3-4",
      "name": "Challenge3-4",
	  "grid": [
        3,
        0
      ],
      "wave": [
        {
          "title": "wave1",
          "enemylist": [
            {
              "index": "FABigChick_Challenge3",
              "level": 90
            },
            {
              "index": "FABigChick_Challenge1",
              "level": 90
            },
            {
              "index": "",
              "level": 0
            },
            {
              "index": "FABigChick_Challenge1",
              "level": 90
            },
            {
              "index": "FABigChick_Challenge1",
              "level": 90
            },
            {
              "index": "Predator_Challenge3",
              "level": 90
            },
            {
              "index": "FABigChick_Challenge3",
              "level": 90
            },
            {
              "index": "FABigChick_Challenge1",
              "level": 90
            },
            {
              "index": "",
              "level": 0
            }
          ]
        }
      ]
    }
  ]
}
